MANIFEST.in
README.md
setup.py
freqens/__init__.py
freqens/analyzer.py
freqens/commands.py
freqens/normalized_counter.py
freqens.egg-info/PKG-INFO
freqens.egg-info/SOURCES.txt
freqens.egg-info/dependency_links.txt
freqens.egg-info/entry_points.txt
freqens.egg-info/requires.txt
freqens.egg-info/top_level.txt