Metadata-Version: 1.1
Name: freqens
Version: 0.0.3
Summary: Library for performing frequency analysis to different formats
Home-page: https://github.com/BraulioVM/freqens
Author: Braulio Valdivielso
Author-email: brlvldvlsmrtnz@gmail.com
License: MIT
Keywords: frequency analysis cryptography
Platform: UNKNOWN
Classifier: Development Status :: 3 - Alpha
Classifier: Intended Audience :: Developers
Classifier: Topic :: Security :: Cryptography
Classifier: License :: OSI Approved :: MIT License
Classifier: Programming Language :: Python :: 2
Classifier: Programming Language :: Python :: 2.6
Classifier: Programming Language :: Python :: 2.7
Classifier: Programming Language :: Python :: 3
Classifier: Programming Language :: Python :: 3.2
Classifier: Programming Language :: Python :: 3.3
Classifier: Programming Language :: Python :: 3.4
